.claude/agents/code-reviewer.md
drs/__init__.py
drs/claude_integration.py
drs/context.py
drs/main.py
drs/reviewer.py
diff_review_system-0.3.0.dist-info/METADATA
diff_review_system-0.3.0.dist-info/WHEEL
diff_review_system-0.3.0.dist-info/entry_points.txt
diff_review_system-0.3.0.dist-info/licenses/LICENSE
diff_review_system-0.3.0.dist-info/RECORD
