Metadata-Version: 2.4
Name: diff-review-system
Version: 0.3.0
Summary: Diff Review System - AI-powered code reviewer based on Claude Code
License: MIT
License-File: LICENSE
Keywords: ai,claude,code-review,diff,gitlab
Classifier: Environment :: Console
Classifier: Intended Audience :: Developers
Classifier: License :: OSI Approved :: MIT License
Classifier: Operating System :: OS Independent
Classifier: Programming Language :: Python :: 3
Classifier: Programming Language :: Python :: 3 :: Only
Classifier: Programming Language :: Python :: 3.12
Classifier: Topic :: Software Development :: Quality Assurance
Requires-Python: >=3.12
Requires-Dist: anyio>=4.0
Requires-Dist: claude-code-sdk
Provides-Extra: dev
Requires-Dist: pre-commit; extra == 'dev'
Requires-Dist: ruff; extra == 'dev'
